<?xml version="1.0" encoding="UTF-8"?>
<qes:espresso xsi:schemaLocation="http://www.quantum-espresso.org/ns/qes/qes-1.0 http://www.quantum-espresso.org/ns/qes/qes_220603.xsd" Units="Hartree atomic units" xmlns:xsi="http://www.w3.org/2001/XMLSchema-instance" xmlns:qes="http://www.quantum-espresso.org/ns/qes/qes-1.0">
  <!--All quantities are in Hartree atomic units unless otherwise specified-->
  <general_info>
    <xml_format NAME="QEXSD" VERSION="21.11.01">QEXSD_21.11.01</xml_format>
    <creator NAME="PWSCF" VERSION="7.1">XML file generated by PWSCF</creator>
    <created DATE="26Jul2024" TIME="21: 5: 4">This run was terminated on:  21: 5: 4  26 Jul 2024</created>
    <job></job>
  </general_info>
  <parallel_info>
    <nprocs>8</nprocs>
    <nthreads>1</nthreads>
    <ntasks>1</ntasks>
    <nbgrp>1</nbgrp>
    <npool>1</npool>
    <ndiag>8</ndiag>
  </parallel_info>
  <input>
    <control_variables>
      <title></title>
      <calculation>scf</calculation>
      <restart_mode>from_scratch</restart_mode>
      <prefix>pwscf</prefix>
      <pseudo_dir>./../potentials/</pseudo_dir>
      <outdir>./</outdir>
      <stress>true</stress>
      <forces>true</forces>
      <wf_collect>true</wf_collect>
      <disk_io>low</disk_io>
      <max_seconds>10000000</max_seconds>
      <nstep>1</nstep>
      <etot_conv_thr>5.000000000000000e-5</etot_conv_thr>
      <forc_conv_thr>5.000000000000000e-4</forc_conv_thr>
      <press_conv_thr>5.000000000000000e-1</press_conv_thr>
      <verbosity>low</verbosity>
      <print_every>100000</print_every>
      <fcp>false</fcp>
      <rism>false</rism>
    </control_variables>
    <atomic_species ntyp="3">
      <species name="C">
        <mass>1.201060000000000e1</mass>
        <pseudo_file>C.pbe-n-kjpaw_psl.1.0.0.UPF</pseudo_file>
      </species>
      <species name="O">
        <mass>1.599940000000000e1</mass>
        <pseudo_file>O.pbe-n-kjpaw_psl.1.0.0.UPF</pseudo_file>
      </species>
      <species name="H">
        <mass>1.007500000000000e0</mass>
        <pseudo_file>H.pbe-kjpaw_psl.1.0.0.UPF</pseudo_file>
      </species>
    </atomic_species>
    <atomic_structure nat="21" alat="3.779452249252e1">
      <atomic_positions>
        <atom name="C" index="1">1.394937243688880e1 1.560167337121659e1 1.199532003498077e1</atom>
        <atom name="C" index="2">1.633811853924450e1 1.620491174471963e1 1.287976855308937e1</atom>
        <atom name="O" index="3">1.325223357225311e1 1.309281627637968e1 1.192388838746992e1</atom>
        <atom name="H" index="4">1.464656799330823e1 1.195472871782381e1 1.248063949830716e1</atom>
        <atom name="C" index="5">1.227847659749470e1 1.746394177525155e1 1.121956856356065e1</atom>
        <atom name="C" index="6">1.302603335513540e1 1.995172842379888e1 1.129683946479660e1</atom>
        <atom name="C" index="7">1.538516744911822e1 2.062352606110335e1 1.218210056513878e1</atom>
        <atom name="C" index="8">1.707091653585188e1 1.874341864245192e1 1.298351451733132e1</atom>
        <atom name="H" index="9">1.043863924255904e1 1.691656370599245e1 1.049863804701592e1</atom>
        <atom name="H" index="10">1.162706910507495e1 2.132253575460242e1 1.070635674263478e1</atom>
        <atom name="C" index="11">1.616156142742071e1 2.329446496564941e1 1.228097103597920e1</atom>
        <atom name="H" index="12">1.897228337340534e1 1.915842139668098e1 1.375748964619430e1</atom>
        <atom name="H" index="13">1.761090577596369e1 1.465962600082940e1 1.343268351989362e1</atom>
        <atom name="C" index="14">1.588441419398310e1 2.480227744048831e1 1.429840485210718e1</atom>
        <atom name="H" index="15">1.701382790962694e1 2.407114240287060e1 1.057328222893863e1</atom>
        <atom name="C" index="16">1.669905622904802e1 2.752990812877314e1 1.440583578229216e1</atom>
        <atom name="H" index="17">1.510180301673058e1 2.412764521399691e1 1.606822785412545e1</atom>
        <atom name="O" index="18">1.937233839398862e1 2.772303813870990e1 1.442571570112322e1</atom>
        <atom name="H" index="19">1.585765567205840e1 2.836951344594437e1 1.608848571818144e1</atom>
        <atom name="H" index="20">1.582277132779780e1 2.840806385888674e1 1.273083923720761e1</atom>
        <atom name="H" index="21">1.998139712395551e1 2.697678529209518e1 1.596773221881785e1</atom>
      </atomic_positions>
      <cell>
        <a1>3.779452249251541e1 0.000000000000000e0 0.000000000000000e0</a1>
        <a2>0.000000000000000e0 3.779452249251541e1 0.000000000000000e0</a2>
        <a3>0.000000000000000e0 0.000000000000000e0 3.779452249251541e1</a3>
      </cell>
    </atomic_structure>
    <dft>
      <functional>PBE</functional>
    </dft>
    <spin>
      <lsda>false</lsda>
      <noncolin>false</noncolin>
      <spinorbit>false</spinorbit>
    </spin>
    <bands>
      <smearing degauss="1.000000000000e-2">mp</smearing>
      <tot_charge>0.000000000000000e0</tot_charge>
      <occupations>smearing</occupations>
    </bands>
    <basis>
      <gamma_only>false</gamma_only>
      <ecutwfc>2.350000000000000e1</ecutwfc>
      <ecutrho>1.630000000000000e2</ecutrho>
    </basis>
    <electron_control>
      <diagonalization>davidson</diagonalization>
      <mixing_mode>plain</mixing_mode>
      <mixing_beta>7.000000000000000e-1</mixing_beta>
      <conv_thr>7.719453021600000e-4</conv_thr>
      <mixing_ndim>8</mixing_ndim>
      <max_nstep>100</max_nstep>
      <real_space_q>false</real_space_q>
      <real_space_beta>false</real_space_beta>
      <tq_smoothing>false</tq_smoothing>
      <tbeta_smoothing>false</tbeta_smoothing>
      <diago_thr_init>0.000000000000000e0</diago_thr_init>
      <diago_full_acc>false</diago_full_acc>
      <diago_cg_maxiter>20</diago_cg_maxiter>
      <diago_ppcg_maxiter>20</diago_ppcg_maxiter>
      <diago_rmm_ndim>4</diago_rmm_ndim>
      <diago_gs_nblock>16</diago_gs_nblock>
      <diago_rmm_conv>false</diago_rmm_conv>
    </electron_control>
    <k_points_IBZ>
      <monkhorst_pack nk1="2" nk2="2" nk3="2" k1="1" k2="1" k3="1">Uniform grid with offset</monkhorst_pack>
    </k_points_IBZ>
    <ion_control>
      <ion_dynamics>none</ion_dynamics>
      <upscale>1.000000000000000e2</upscale>
      <remove_rigid_rot>false</remove_rigid_rot>
      <refold_pos>false</refold_pos>
    </ion_control>
    <cell_control>
      <cell_dynamics>none</cell_dynamics>
      <pressure>0.000000000000000e0</pressure>
      <wmass>1.501691999999999e2</wmass>
      <cell_do_free>all</cell_do_free>
    </cell_control>
    <symmetry_flags>
      <nosym>false</nosym>
      <nosym_evc>false</nosym_evc>
      <noinv>false</noinv>
      <no_t_rev>false</no_t_rev>
      <force_symmorphic>false</force_symmorphic>
      <use_all_frac>false</use_all_frac>
    </symmetry_flags>
  </input>
  <output>
    <convergence_info>
      <scf_conv>
        <convergence_achieved>true</convergence_achieved>
        <n_scf_steps>8</n_scf_steps>
        <scf_error>5.678152021503574e-4</scf_error>
      </scf_conv>
    </convergence_info>
    <algorithmic_info>
      <real_space_q>false</real_space_q>
      <real_space_beta>false</real_space_beta>
      <uspp>true</uspp>
      <paw>true</paw>
    </algorithmic_info>
    <atomic_species ntyp="3" pseudo_dir="./../potentials/">
      <species name="C">
        <mass>1.201060000000000e1</mass>
        <pseudo_file>C.pbe-n-kjpaw_psl.1.0.0.UPF</pseudo_file>
      </species>
      <species name="O">
        <mass>1.599940000000000e1</mass>
        <pseudo_file>O.pbe-n-kjpaw_psl.1.0.0.UPF</pseudo_file>
      </species>
      <species name="H">
        <mass>1.007500000000000e0</mass>
        <pseudo_file>H.pbe-kjpaw_psl.1.0.0.UPF</pseudo_file>
      </species>
    </atomic_species>
    <atomic_structure nat="21" alat="1.889726124626e0">
      <atomic_positions>
        <atom name="C" index="1">1.394937243688880e1 1.560167337121659e1 1.199532003498077e1</atom>
        <atom name="C" index="2">1.633811853924450e1 1.620491174471963e1 1.287976855308937e1</atom>
        <atom name="O" index="3">1.325223357225311e1 1.309281627637968e1 1.192388838746992e1</atom>
        <atom name="H" index="4">1.464656799330823e1 1.195472871782381e1 1.248063949830716e1</atom>
        <atom name="C" index="5">1.227847659749470e1 1.746394177525155e1 1.121956856356065e1</atom>
        <atom name="C" index="6">1.302603335513540e1 1.995172842379888e1 1.129683946479660e1</atom>
        <atom name="C" index="7">1.538516744911822e1 2.062352606110335e1 1.218210056513878e1</atom>
        <atom name="C" index="8">1.707091653585188e1 1.874341864245192e1 1.298351451733132e1</atom>
        <atom name="H" index="9">1.043863924255904e1 1.691656370599245e1 1.049863804701592e1</atom>
        <atom name="H" index="10">1.162706910507495e1 2.132253575460242e1 1.070635674263478e1</atom>
        <atom name="C" index="11">1.616156142742071e1 2.329446496564941e1 1.228097103597920e1</atom>
        <atom name="H" index="12">1.897228337340534e1 1.915842139668098e1 1.375748964619430e1</atom>
        <atom name="H" index="13">1.761090577596369e1 1.465962600082940e1 1.343268351989362e1</atom>
        <atom name="C" index="14">1.588441419398310e1 2.480227744048831e1 1.429840485210718e1</atom>
        <atom name="H" index="15">1.701382790962694e1 2.407114240287060e1 1.057328222893863e1</atom>
        <atom name="C" index="16">1.669905622904802e1 2.752990812877314e1 1.440583578229216e1</atom>
        <atom name="H" index="17">1.510180301673058e1 2.412764521399691e1 1.606822785412545e1</atom>
        <atom name="O" index="18">1.937233839398862e1 2.772303813870990e1 1.442571570112322e1</atom>
        <atom name="H" index="19">1.585765567205840e1 2.836951344594437e1 1.608848571818144e1</atom>
        <atom name="H" index="20">1.582277132779780e1 2.840806385888674e1 1.273083923720761e1</atom>
        <atom name="H" index="21">1.998139712395551e1 2.697678529209518e1 1.596773221881785e1</atom>
      </atomic_positions>
      <cell>
        <a1>3.779452249251541e1 0.000000000000000e0 0.000000000000000e0</a1>
        <a2>0.000000000000000e0 3.779452249251541e1 0.000000000000000e0</a2>
        <a3>0.000000000000000e0 0.000000000000000e0 3.779452249251541e1</a3>
      </cell>
    </atomic_structure>
    <symmetries>
      <nsym>1</nsym>
      <nrot>48</nrot>
      <space_group>0</space_group>
      <symmetry>
        <info name="identity">crystal_symmetry</info>
        <rotation rank="2" dims="3 3">
          1.000000000000000e0 0.000000000000000e0 0.000000000000000e0
          0.000000000000000e0 1.000000000000000e0 0.000000000000000e0
          0.000000000000000e0 0.000000000000000e0 1.000000000000000e0
          </rotation>
        <fractional_translation>0.000000000000000e0 0.000000000000000e0 0.000000000000000e0</fractional_translation>
        <equivalent_atoms size="21" nat="21">
          1 2 3 4 5 6 7 8
          9 10 11 12 13 14 15 16
          17 18 19 20 21
          </equivalent_atoms>
      </symmetry>
      <symmetry>
        <info name="180 deg rotation - cart. axis [0,0,1]">lattice_symmetry</info>
        <rotation rank="2" dims="3 3">
          -1.000000000000000e0 0.000000000000000e0 0.000000000000000e0
          0.000000000000000e0 -1.000000000000000e0 0.000000000000000e0
          0.000000000000000e0 0.000000000000000e0 1.000000000000000e0
          </rotation>
      </symmetry>
      <symmetry>
        <info name="180 deg rotation - cart. axis [0,1,0]">lattice_symmetry</info>
        <rotation rank="2" dims="3 3">
          -1.000000000000000e0 0.000000000000000e0 0.000000000000000e0
          0.000000000000000e0 1.000000000000000e0 0.000000000000000e0
          0.000000000000000e0 0.000000000000000e0 -1.000000000000000e0
          </rotation>
      </symmetry>
      <symmetry>
        <info name="180 deg rotation - cart. axis [1,0,0]">lattice_symmetry</info>
        <rotation rank="2" dims="3 3">
          1.000000000000000e0 0.000000000000000e0 0.000000000000000e0
          0.000000000000000e0 -1.000000000000000e0 0.000000000000000e0
          0.000000000000000e0 0.000000000000000e0 -1.000000000000000e0
          </rotation>
      </symmetry>
      <symmetry>
        <info name="180 deg rotation - cart. axis [1,1,0]">lattice_symmetry</info>
        <rotation rank="2" dims="3 3">
          0.000000000000000e0 1.000000000000000e0 0.000000000000000e0
          1.000000000000000e0 0.000000000000000e0 0.000000000000000e0
          0.000000000000000e0 0.000000000000000e0 -1.000000000000000e0
          </rotation>
      </symmetry>
      <symmetry>
        <info name="180 deg rotation - cart. axis [1,-1,0]">lattice_symmetry</info>
        <rotation rank="2" dims="3 3">
          0.000000000000000e0 -1.000000000000000e0 0.000000000000000e0
          -1.000000000000000e0 0.000000000000000e0 0.000000000000000e0
          0.000000000000000e0 0.000000000000000e0 -1.000000000000000e0
          </rotation>
      </symmetry>
      <symmetry>
        <info name=" 90 deg rotation - cart. axis [0,0,-1]">lattice_symmetry</info>
        <rotation rank="2" dims="3 3">
          0.000000000000000e0 1.000000000000000e0 0.000000000000000e0
          -1.000000000000000e0 0.000000000000000e0 0.000000000000000e0
          0.000000000000000e0 0.000000000000000e0 1.000000000000000e0
          </rotation>
      </symmetry>
      <symmetry>
        <info name=" 90 deg rotation - cart. axis [0,0,1]">lattice_symmetry</info>
        <rotation rank="2" dims="3 3">
          0.000000000000000e0 -1.000000000000000e0 0.000000000000000e0
          1.000000000000000e0 0.000000000000000e0 0.000000000000000e0
          0.000000000000000e0 0.000000000000000e0 1.000000000000000e0
          </rotation>
      </symmetry>
      <symmetry>
        <info name="180 deg rotation - cart. axis [1,0,1]">lattice_symmetry</info>
        <rotation rank="2" dims="3 3">
          0.000000000000000e0 0.000000000000000e0 1.000000000000000e0
          0.000000000000000e0 -1.000000000000000e0 0.000000000000000e0
          1.000000000000000e0 0.000000000000000e0 0.000000000000000e0
          </rotation>
      </symmetry>
      <symmetry>
        <info name="180 deg rotation - cart. axis [-1,0,1]">lattice_symmetry</info>
        <rotation rank="2" dims="3 3">
          0.000000000000000e0 0.000000000000000e0 -1.000000000000000e0
          0.000000000000000e0 -1.000000000000000e0 0.000000000000000e0
          -1.000000000000000e0 0.000000000000000e0 0.000000000000000e0
          </rotation>
      </symmetry>
      <symmetry>
        <info name=" 90 deg rotation - cart. axis [0,1,0]">lattice_symmetry</info>
        <rotation rank="2" dims="3 3">
          0.000000000000000e0 0.000000000000000e0 1.000000000000000e0
          0.000000000000000e0 1.000000000000000e0 0.000000000000000e0
          -1.000000000000000e0 0.000000000000000e0 0.000000000000000e0
          </rotation>
      </symmetry>
      <symmetry>
        <info name=" 90 deg rotation - cart. axis [0,-1,0]">lattice_symmetry</info>
        <rotation rank="2" dims="3 3">
          0.000000000000000e0 0.000000000000000e0 -1.000000000000000e0
          0.000000000000000e0 1.000000000000000e0 0.000000000000000e0
          1.000000000000000e0 0.000000000000000e0 0.000000000000000e0
          </rotation>
      </symmetry>
      <symmetry>
        <info name="180 deg rotation - cart. axis [0,1,1]">lattice_symmetry</info>
        <rotation rank="2" dims="3 3">
          -1.000000000000000e0 0.000000000000000e0 0.000000000000000e0
          0.000000000000000e0 0.000000000000000e0 1.000000000000000e0
          0.000000000000000e0 1.000000000000000e0 0.000000000000000e0
          </rotation>
      </symmetry>
      <symmetry>
        <info name="180 deg rotation - cart. axis [0,1,-1]">lattice_symmetry</info>
        <rotation rank="2" dims="3 3">
          -1.000000000000000e0 0.000000000000000e0 0.000000000000000e0
          0.000000000000000e0 0.000000000000000e0 -1.000000000000000e0
          0.000000000000000e0 -1.000000000000000e0 0.000000000000000e0
          </rotation>
      </symmetry>
      <symmetry>
        <info name=" 90 deg rotation - cart. axis [-1,0,0]">lattice_symmetry</info>
        <rotation rank="2" dims="3 3">
          1.000000000000000e0 0.000000000000000e0 0.000000000000000e0
          0.000000000000000e0 0.000000000000000e0 1.000000000000000e0
          0.000000000000000e0 -1.000000000000000e0 0.000000000000000e0
          </rotation>
      </symmetry>
      <symmetry>
        <info name=" 90 deg rotation - cart. axis [1,0,0]">lattice_symmetry</info>
        <rotation rank="2" dims="3 3">
          1.000000000000000e0 0.000000000000000e0 0.000000000000000e0
          0.000000000000000e0 0.000000000000000e0 -1.000000000000000e0
          0.000000000000000e0 1.000000000000000e0 0.000000000000000e0
          </rotation>
      </symmetry>
      <symmetry>
        <info name="120 deg rotation - cart. axis [-1,-1,-1]">lattice_symmetry</info>
        <rotation rank="2" dims="3 3">
          0.000000000000000e0 1.000000000000000e0 0.000000000000000e0
          0.000000000000000e0 0.000000000000000e0 1.000000000000000e0
          1.000000000000000e0 0.000000000000000e0 0.000000000000000e0
          </rotation>
      </symmetry>
      <symmetry>
        <info name="120 deg rotation - cart. axis [-1,1,1]">lattice_symmetry</info>
        <rotation rank="2" dims="3 3">
          0.000000000000000e0 -1.000000000000000e0 0.000000000000000e0
          0.000000000000000e0 0.000000000000000e0 1.000000000000000e0
          -1.000000000000000e0 0.000000000000000e0 0.000000000000000e0
          </rotation>
      </symmetry>
      <symmetry>
        <info name="120 deg rotation - cart. axis [1,1,-1]">lattice_symmetry</info>
        <rotation rank="2" dims="3 3">
          0.000000000000000e0 1.000000000000000e0 0.000000000000000e0
          0.000000000000000e0 0.000000000000000e0 -1.000000000000000e0
          -1.000000000000000e0 0.000000000000000e0 0.000000000000000e0
          </rotation>
      </symmetry>
      <symmetry>
        <info name="120 deg rotation - cart. axis [1,-1,1]">lattice_symmetry</info>
        <rotation rank="2" dims="3 3">
          0.000000000000000e0 -1.000000000000000e0 0.000000000000000e0
          0.000000000000000e0 0.000000000000000e0 -1.000000000000000e0
          1.000000000000000e0 0.000000000000000e0 0.000000000000000e0
          </rotation>
      </symmetry>
      <symmetry>
        <info name="120 deg rotation - cart. axis [1,1,1]">lattice_symmetry</info>
        <rotation rank="2" dims="3 3">
          0.000000000000000e0 0.000000000000000e0 1.000000000000000e0
          1.000000000000000e0 0.000000000000000e0 0.000000000000000e0
          0.000000000000000e0 1.000000000000000e0 0.000000000000000e0
          </rotation>
      </symmetry>
      <symmetry>
        <info name="120 deg rotation - cart. axis [-1,1,-1]">lattice_symmetry</info>
        <rotation rank="2" dims="3 3">
          0.000000000000000e0 0.000000000000000e0 1.000000000000000e0
          -1.000000000000000e0 0.000000000000000e0 0.000000000000000e0
          0.000000000000000e0 -1.000000000000000e0 0.000000000000000e0
          </rotation>
      </symmetry>
      <symmetry>
        <info name="120 deg rotation - cart. axis [1,-1,-1]">lattice_symmetry</info>
        <rotation rank="2" dims="3 3">
          0.000000000000000e0 0.000000000000000e0 -1.000000000000000e0
          -1.000000000000000e0 0.000000000000000e0 0.000000000000000e0
          0.000000000000000e0 1.000000000000000e0 0.000000000000000e0
          </rotation>
      </symmetry>
      <symmetry>
        <info name="120 deg rotation - cart. axis [-1,-1,1]">lattice_symmetry</info>
        <rotation rank="2" dims="3 3">
          0.000000000000000e0 0.000000000000000e0 -1.000000000000000e0
          1.000000000000000e0 0.000000000000000e0 0.000000000000000e0
          0.000000000000000e0 -1.000000000000000e0 0.000000000000000e0
          </rotation>
      </symmetry>
      <symmetry>
        <info name="inversion">lattice_symmetry</info>
        <rotation rank="2" dims="3 3">
          -1.000000000000000e0 0.000000000000000e0 0.000000000000000e0
          0.000000000000000e0 -1.000000000000000e0 0.000000000000000e0
          0.000000000000000e0 0.000000000000000e0 -1.000000000000000e0
          </rotation>
      </symmetry>
      <symmetry>
        <info name="inv. 180 deg rotation - cart. axis [0,0,1]">lattice_symmetry</info>
        <rotation rank="2" dims="3 3">
          1.000000000000000e0 0.000000000000000e0 0.000000000000000e0
          0.000000000000000e0 1.000000000000000e0 0.000000000000000e0
          0.000000000000000e0 0.000000000000000e0 -1.000000000000000e0
          </rotation>
      </symmetry>
      <symmetry>
        <info name="inv. 180 deg rotation - cart. axis [0,1,0]">lattice_symmetry</info>
        <rotation rank="2" dims="3 3">
          1.000000000000000e0 0.000000000000000e0 0.000000000000000e0
          0.000000000000000e0 -1.000000000000000e0 0.000000000000000e0
          0.000000000000000e0 0.000000000000000e0 1.000000000000000e0
          </rotation>
      </symmetry>
      <symmetry>
        <info name="inv. 180 deg rotation - cart. axis [1,0,0]">lattice_symmetry</info>
        <rotation rank="2" dims="3 3">
          -1.000000000000000e0 0.000000000000000e0 0.000000000000000e0
          0.000000000000000e0 1.000000000000000e0 0.000000000000000e0
          0.000000000000000e0 0.000000000000000e0 1.000000000000000e0
          </rotation>
      </symmetry>
      <symmetry>
        <info name="inv. 180 deg rotation - cart. axis [1,1,0]">lattice_symmetry</info>
        <rotation rank="2" dims="3 3">
          0.000000000000000e0 -1.000000000000000e0 0.000000000000000e0
          -1.000000000000000e0 0.000000000000000e0 0.000000000000000e0
          0.000000000000000e0 0.000000000000000e0 1.000000000000000e0
          </rotation>
      </symmetry>
      <symmetry>
        <info name="inv. 180 deg rotation - cart. axis [1,-1,0]">lattice_symmetry</info>
        <rotation rank="2" dims="3 3">
          0.000000000000000e0 1.000000000000000e0 0.000000000000000e0
          1.000000000000000e0 0.000000000000000e0 0.000000000000000e0
          0.000000000000000e0 0.000000000000000e0 1.000000000000000e0
          </rotation>
      </symmetry>
      <symmetry>
        <info name="inv.  90 deg rotation - cart. axis [0,0,-1]">lattice_symmetry</info>
        <rotation rank="2" dims="3 3">
          0.000000000000000e0 -1.000000000000000e0 0.000000000000000e0
          1.000000000000000e0 0.000000000000000e0 0.000000000000000e0
          0.000000000000000e0 0.000000000000000e0 -1.000000000000000e0
          </rotation>
      </symmetry>
      <symmetry>
        <info name="inv.  90 deg rotation - cart. axis [0,0,1]">lattice_symmetry</info>
        <rotation rank="2" dims="3 3">
          0.000000000000000e0 1.000000000000000e0 0.000000000000000e0
          -1.000000000000000e0 0.000000000000000e0 0.000000000000000e0
          0.000000000000000e0 0.000000000000000e0 -1.000000000000000e0
          </rotation>
      </symmetry>
      <symmetry>
        <info name="inv. 180 deg rotation - cart. axis [1,0,1]">lattice_symmetry</info>
        <rotation rank="2" dims="3 3">
          0.000000000000000e0 0.000000000000000e0 -1.000000000000000e0
          0.000000000000000e0 1.000000000000000e0 0.000000000000000e0
          -1.000000000000000e0 0.000000000000000e0 0.000000000000000e0
          </rotation>
      </symmetry>
      <symmetry>
        <info name="inv. 180 deg rotation - cart. axis [-1,0,1]">lattice_symmetry</info>
        <rotation rank="2" dims="3 3">
          0.000000000000000e0 0.000000000000000e0 1.000000000000000e0
          0.000000000000000e0 1.000000000000000e0 0.000000000000000e0
          1.000000000000000e0 0.000000000000000e0 0.000000000000000e0
          </rotation>
      </symmetry>
      <symmetry>
        <info name="inv.  90 deg rotation - cart. axis [0,1,0]">lattice_symmetry</info>
        <rotation rank="2" dims="3 3">
          0.000000000000000e0 0.000000000000000e0 -1.000000000000000e0
          0.000000000000000e0 -1.000000000000000e0 0.000000000000000e0
          1.000000000000000e0 0.000000000000000e0 0.000000000000000e0
          </rotation>
      </symmetry>
      <symmetry>
        <info name="inv.  90 deg rotation - cart. axis [0,-1,0]">lattice_symmetry</info>
        <rotation rank="2" dims="3 3">
          0.000000000000000e0 0.000000000000000e0 1.000000000000000e0
          0.000000000000000e0 -1.000000000000000e0 0.000000000000000e0
          -1.000000000000000e0 0.000000000000000e0 0.000000000000000e0
          </rotation>
      </symmetry>
      <symmetry>
        <info name="inv. 180 deg rotation - cart. axis [0,1,1]">lattice_symmetry</info>
        <rotation rank="2" dims="3 3">
          1.000000000000000e0 0.000000000000000e0 0.000000000000000e0
          0.000000000000000e0 0.000000000000000e0 -1.000000000000000e0
          0.000000000000000e0 -1.000000000000000e0 0.000000000000000e0
          </rotation>
      </symmetry>
      <symmetry>
        <info name="inv. 180 deg rotation - cart. axis [0,1,-1]">lattice_symmetry</info>
        <rotation rank="2" dims="3 3">
          1.000000000000000e0 0.000000000000000e0 0.000000000000000e0
          0.000000000000000e0 0.000000000000000e0 1.000000000000000e0
          0.000000000000000e0 1.000000000000000e0 0.000000000000000e0
          </rotation>
      </symmetry>
      <symmetry>
        <info name="inv.  90 deg rotation - cart. axis [-1,0,0]">lattice_symmetry</info>
        <rotation rank="2" dims="3 3">
          -1.000000000000000e0 0.000000000000000e0 0.000000000000000e0
          0.000000000000000e0 0.000000000000000e0 -1.000000000000000e0
          0.000000000000000e0 1.000000000000000e0 0.000000000000000e0
          </rotation>
      </symmetry>
      <symmetry>
        <info name="inv.  90 deg rotation - cart. axis [1,0,0]">lattice_symmetry</info>
        <rotation rank="2" dims="3 3">
          -1.000000000000000e0 0.000000000000000e0 0.000000000000000e0
          0.000000000000000e0 0.000000000000000e0 1.000000000000000e0
          0.000000000000000e0 -1.000000000000000e0 0.000000000000000e0
          </rotation>
      </symmetry>
      <symmetry>
        <info name="inv. 120 deg rotation - cart. axis [-1,-1,-1]">lattice_symmetry</info>
        <rotation rank="2" dims="3 3">
          0.000000000000000e0 -1.000000000000000e0 0.000000000000000e0
          0.000000000000000e0 0.000000000000000e0 -1.000000000000000e0
          -1.000000000000000e0 0.000000000000000e0 0.000000000000000e0
          </rotation>
      </symmetry>
      <symmetry>
        <info name="inv. 120 deg rotation - cart. axis [-1,1,1]">lattice_symmetry</info>
        <rotation rank="2" dims="3 3">
          0.000000000000000e0 1.000000000000000e0 0.000000000000000e0
          0.000000000000000e0 0.000000000000000e0 -1.000000000000000e0
          1.000000000000000e0 0.000000000000000e0 0.000000000000000e0
          </rotation>
      </symmetry>
      <symmetry>
        <info name="inv. 120 deg rotation - cart. axis [1,1,-1]">lattice_symmetry</info>
        <rotation rank="2" dims="3 3">
          0.000000000000000e0 -1.000000000000000e0 0.000000000000000e0
          0.000000000000000e0 0.000000000000000e0 1.000000000000000e0
          1.000000000000000e0 0.000000000000000e0 0.000000000000000e0
          </rotation>
      </symmetry>
      <symmetry>
        <info name="inv. 120 deg rotation - cart. axis [1,-1,1]">lattice_symmetry</info>
        <rotation rank="2" dims="3 3">
          0.000000000000000e0 1.000000000000000e0 0.000000000000000e0
          0.000000000000000e0 0.000000000000000e0 1.000000000000000e0
          -1.000000000000000e0 0.000000000000000e0 0.000000000000000e0
          </rotation>
      </symmetry>
      <symmetry>
        <info name="inv. 120 deg rotation - cart. axis [1,1,1]">lattice_symmetry</info>
        <rotation rank="2" dims="3 3">
          0.000000000000000e0 0.000000000000000e0 -1.000000000000000e0
          -1.000000000000000e0 0.000000000000000e0 0.000000000000000e0
          0.000000000000000e0 -1.000000000000000e0 0.000000000000000e0
          </rotation>
      </symmetry>
      <symmetry>
        <info name="inv. 120 deg rotation - cart. axis [-1,1,-1]">lattice_symmetry</info>
        <rotation rank="2" dims="3 3">
          0.000000000000000e0 0.000000000000000e0 -1.000000000000000e0
          1.000000000000000e0 0.000000000000000e0 0.000000000000000e0
          0.000000000000000e0 1.000000000000000e0 0.000000000000000e0
          </rotation>
      </symmetry>
      <symmetry>
        <info name="inv. 120 deg rotation - cart. axis [1,-1,-1]">lattice_symmetry</info>
        <rotation rank="2" dims="3 3">
          0.000000000000000e0 0.000000000000000e0 1.000000000000000e0
          1.000000000000000e0 0.000000000000000e0 0.000000000000000e0
          0.000000000000000e0 -1.000000000000000e0 0.000000000000000e0
          </rotation>
      </symmetry>
      <symmetry>
        <info name="inv. 120 deg rotation - cart. axis [-1,-1,1]">lattice_symmetry</info>
        <rotation rank="2" dims="3 3">
          0.000000000000000e0 0.000000000000000e0 1.000000000000000e0
          -1.000000000000000e0 0.000000000000000e0 0.000000000000000e0
          0.000000000000000e0 1.000000000000000e0 0.000000000000000e0
          </rotation>
      </symmetry>
    </symmetries>
    <basis_set>
      <gamma_only>false</gamma_only>
      <ecutwfc>2.350000000000000e1</ecutwfc>
      <ecutrho>1.630000000000000e2</ecutrho>
      <fft_grid nr1="225" nr2="225" nr3="225"></fft_grid>
      <fft_smooth nr1="180" nr2="180" nr3="180"></fft_smooth>
      <fft_box nr1="225" nr2="225" nr3="225"></fft_box>
      <ngm>5366705</ngm>
      <ngms>2350229</ngms>
      <npwx>293697</npwx>
      <reciprocal_lattice>
        <b1>5.000000000000000e-2 0.000000000000000e0 0.000000000000000e0</b1>
        <b2>0.000000000000000e0 5.000000000000000e-2 0.000000000000000e0</b2>
        <b3>0.000000000000000e0 0.000000000000000e0 5.000000000000000e-2</b3>
      </reciprocal_lattice>
    </basis_set>
    <dft>
      <functional>PBE</functional>
    </dft>
    <magnetization>
      <lsda>false</lsda>
      <noncolin>false</noncolin>
      <spinorbit>false</spinorbit>
      <absolute>0.000000000000000e0</absolute>
    </magnetization>
    <total_energy>
      <etot>-1.304687144580824e2</etot>
      <eband>-2.685022301084658e1</eband>
      <ehart>2.336339316232390e2</ehart>
      <vtxc>-3.469332292374796e1</vtxc>
      <etxc>-3.177779626091677e1</etxc>
      <ewald>1.635704945697001e2</ewald>
      <demet>1.235902561411332e-23</demet>
    </total_energy>
    <band_structure>
      <lsda>false</lsda>
      <noncolin>false</noncolin>
      <spinorbit>false</spinorbit>
      <nbnd>35</nbnd>
      <nelec>5.800000000000001e1</nelec>
      <num_of_atomic_wfc>54</num_of_atomic_wfc>
      <wf_collected>true</wf_collected>
      <fermi_energy>-1.233370624975860e-1</fermi_energy>
      <starting_k_points>
        <monkhorst_pack nk1="2" nk2="2" nk3="2" k1="1" k2="1" k3="1">Uniform grid with offset</monkhorst_pack>
      </starting_k_points>
      <nks>4</nks>
      <occupations_kind>smearing</occupations_kind>
      <smearing degauss="1.000000000000e-2">mp</smearing>
      <ks_energies>
        <k_point weight="5.000000000000e-1">1.250000000000000e-2 1.250000000000000e-2 1.250000000000000e-2</k_point>
        <npw>293697</npw>
        <eigenvalues size="35">
          -9.634541071931944e-1 -9.343257763872590e-1 -7.842229999934023e-1 -7.195699028566336e-1 -6.807308191235590e-1
          -6.696202668139968e-1 -6.076905343933499e-1 -5.610924774601592e-1 -5.445417730876573e-1 -5.065120551170552e-1
          -4.913703536809369e-1 -4.538671290508570e-1 -4.399156103409253e-1 -4.207197819821433e-1 -3.945921799711058e-1
          -3.936174282418910e-1 -3.792749591531194e-1 -3.755840322051886e-1 -3.632991143729288e-1 -3.514309952458512e-1
          -3.358451581413802e-1 -3.110383941979697e-1 -2.944316269658949e-1 -2.915031147314201e-1 -2.740364676580074e-1
          -2.404431178576114e-1 -2.320256181369007e-1 -2.150944738453458e-1 -1.952605950678116e-1 -5.043988740809046e-2
          -3.752556917051744e-2 -2.724155319728665e-2 -2.507483227417013e-2 -1.506679747744576e-2 -6.514773083235324e-3
          </eigenvalues>
        <occupations size="35">
          1.000000000000000e0 1.000000000000000e0 1.000000000000000e0 1.000000000000000e0 1.000000000000000e0
          1.000000000000000e0 1.000000000000000e0 1.000000000000000e0 1.000000000000000e0 1.000000000000000e0
          1.000000000000000e0 1.000000000000000e0 1.000000000000000e0 1.000000000000000e0 1.000000000000000e0
          1.000000000000000e0 1.000000000000000e0 1.000000000000000e0 1.000000000000000e0 1.000000000000000e0
          1.000000000000000e0 1.000000000000000e0 1.000000000000000e0 1.000000000000000e0 1.000000000000000e0
          1.000000000000000e0 1.000000000000000e0 1.000000000000000e0 1.000000000000000e0 -1.684731974842400e-23
          -2.501956760011310e-32 -2.109287370641328e-40 -3.199837623452644e-42 -3.726014674404698e-51 -1.756418008397886e-59
          </occupations>
      </ks_energies>
      <ks_energies>
        <k_point weight="5.000000000000e-1">-1.250000000000000e-2 -1.250000000000000e-2 1.250000000000000e-2</k_point>
        <npw>293697</npw>
        <eigenvalues size="35">
          -9.634541040535915e-1 -9.343257569950277e-1 -7.842230454703808e-1 -7.195699711111248e-1 -6.807308460831041e-1
          -6.696202738644050e-1 -6.076905001725855e-1 -5.610925442833905e-1 -5.445417554552416e-1 -5.065120858242079e-1
          -4.913704563181926e-1 -4.538671995235769e-1 -4.399156202130672e-1 -4.207197985075577e-1 -3.945921485375202e-1
          -3.936174016586071e-1 -3.792750215839303e-1 -3.755840503242265e-1 -3.632991288792826e-1 -3.514310234171703e-1
          -3.358451120459185e-1 -3.110384295596087e-1 -2.944315920359276e-1 -2.915031112385640e-1 -2.740364990093099e-1
          -2.404432727577697e-1 -2.320256246161947e-1 -2.150949700135737e-1 -1.952605456567476e-1 -5.043785124182493e-2
          -3.751956172403906e-2 -2.725858770106546e-2 -2.507628110121185e-2 -1.506128758996550e-2 -6.386971413612361e-3
          </eigenvalues>
        <occupations size="35">
          1.000000000000000e0 1.000000000000000e0 1.000000000000000e0 1.000000000000000e0 1.000000000000000e0
          1.000000000000000e0 1.000000000000000e0 1.000000000000000e0 1.000000000000000e0 1.000000000000000e0
          1.000000000000000e0 1.000000000000000e0 1.000000000000000e0 1.000000000000000e0 1.000000000000000e0
          1.000000000000000e0 1.000000000000000e0 1.000000000000000e0 1.000000000000000e0 1.000000000000000e0
          1.000000000000000e0 1.000000000000000e0 1.000000000000000e0 1.000000000000000e0 1.000000000000000e0
          1.000000000000000e0 1.000000000000000e0 1.000000000000000e0 1.000000000000000e0 -1.679786685474763e-23
          -2.476470885405639e-32 -2.179084670738950e-40 -3.208913140527192e-42 -3.682012672442254e-51 -1.304240527606657e-59
          </occupations>
      </ks_energies>
      <ks_energies>
        <k_point weight="5.000000000000e-1">-1.250000000000000e-2 1.250000000000000e-2 -1.250000000000000e-2</k_point>
        <npw>293697</npw>
        <eigenvalues size="35">
          -9.634541238614716e-1 -9.343257353036975e-1 -7.842230146698020e-1 -7.195699307309007e-1 -6.807308288484728e-1
          -6.696202008868757e-1 -6.076905537837558e-1 -5.610925072118613e-1 -5.445417926209435e-1 -5.065120951924110e-1
          -4.913704427415738e-1 -4.538671825744117e-1 -4.399156185707294e-1 -4.207198102659230e-1 -3.945921840878810e-1
          -3.936174030448699e-1 -3.792749404314734e-1 -3.755840250501222e-1 -3.632991233519345e-1 -3.514310230322593e-1
          -3.358451309697428e-1 -3.110384385347193e-1 -2.944316349309103e-1 -2.915031090656551e-1 -2.740364936934965e-1
          -2.404431668533119e-1 -2.320256239328262e-1 -2.150946827944174e-1 -1.952606211878905e-1 -5.043912781808231e-2
          -3.752235269010024e-2 -2.724040305570741e-2 -2.507656326110543e-2 -1.504126265577402e-2 -6.730431270073928e-3
          </eigenvalues>
        <occupations size="35">
          1.000000000000000e0 1.000000000000000e0 1.000000000000000e0 1.000000000000000e0 1.000000000000000e0
          1.000000000000000e0 1.000000000000000e0 1.000000000000000e0 1.000000000000000e0 1.000000000000000e0
          1.000000000000000e0 1.000000000000000e0 1.000000000000000e0 1.000000000000000e0 1.000000000000000e0
          1.000000000000000e0 1.000000000000000e0 1.000000000000000e0 1.000000000000000e0 1.000000000000000e0
          1.000000000000000e0 1.000000000000000e0 1.000000000000000e0 1.000000000000000e0 1.000000000000000e0
          1.000000000000000e0 1.000000000000000e0 1.000000000000000e0 1.000000000000000e0 -1.682885455290901e-23
          -2.488279000927460e-32 -2.104655713647135e-40 -3.210683579228228e-42 -3.526406241585297e-51 -2.900288507371673e-59
          </occupations>
      </ks_energies>
      <ks_energies>
        <k_point weight="5.000000000000e-1">1.250000000000000e-2 -1.250000000000000e-2 -1.250000000000000e-2</k_point>
        <npw>293697</npw>
        <eigenvalues size="35">
          -9.634541129393687e-1 -9.343258074018209e-1 -7.842229706859931e-1 -7.195700031220666e-1 -6.807308276860640e-1
          -6.696202680142540e-1 -6.076905685499778e-1 -5.610925348952285e-1 -5.445417590739366e-1 -5.065120640198602e-1
          -4.913704499509072e-1 -4.538671894289516e-1 -4.399156722337628e-1 -4.207198036471509e-1 -3.945920986739412e-1
          -3.936174840470430e-1 -3.792749296952362e-1 -3.755840531034161e-1 -3.632991645297579e-1 -3.514310787612913e-1
          -3.358451342273285e-1 -3.110384508255493e-1 -2.944316411263934e-1 -2.915031560179573e-1 -2.740366077138552e-1
          -2.404431253302140e-1 -2.320256246218072e-1 -2.150946559698936e-1 -1.952605946924172e-1 -5.043804105517403e-2
          -3.752117530688649e-2 -2.724798690141901e-2 -2.507558119512561e-2 -1.504792515893522e-2 -6.497475830448687e-3
          </eigenvalues>
        <occupations size="35">
          1.000000000000000e0 1.000000000000000e0 1.000000000000000e0 1.000000000000000e0 1.000000000000000e0
          1.000000000000000e0 1.000000000000000e0 1.000000000000000e0 1.000000000000000e0 1.000000000000000e0
          1.000000000000000e0 1.000000000000000e0 1.000000000000000e0 1.000000000000000e0 1.000000000000000e0
          1.000000000000000e0 1.000000000000000e0 1.000000000000000e0 1.000000000000000e0 1.000000000000000e0
          1.000000000000000e0 1.000000000000000e0 1.000000000000000e0 1.000000000000000e0 1.000000000000000e0
          1.000000000000000e0 1.000000000000000e0 1.000000000000000e0 1.000000000000000e0 -1.680247081797097e-23
          -2.483290884485579e-32 -2.135383669297406e-40 -3.204525705175281e-42 -3.577437264545949e-51 -1.687097590718760e-59
          </occupations>
      </ks_energies>
    </band_structure>
    <forces rank="2" dims="3 21">
      8.736794319059085e-3 -2.394360874806436e-2 5.343311803187701e-3
      9.470196624076124e-3 9.848943060392429e-3 7.450972100497987e-4
      -3.373041901225505e-4 -1.120573716011012e-2 -1.119152084998535e-3
      -1.317882457069297e-2 1.879662836284973e-2 -5.916447857365768e-3
      -5.982714849164443e-3 -1.661602864299988e-2 -4.548055730753376e-3
      -1.223547692545110e-2 -6.625086445107533e-4 -2.907515589934015e-3
      2.084099630927230e-2 8.960217957907844e-3 8.337741074599686e-3
      7.415253443888848e-3 -1.300917660450402e-2 4.781118803165118e-3
      -3.581195921050922e-3 -3.367101400031768e-4 -2.095897170589543e-4
      1.612924372586467e-3 9.413390881912012e-3 -2.080968997380417e-3
      -3.160715093622561e-3 9.078045735466356e-3 7.358797801746171e-3
      -1.041386804095391e-2 4.221497539742449e-3 -6.686658474445922e-3
      -3.751560340882162e-4 5.446874973536834e-3 7.143456253719267e-4
      7.249829375022444e-4 -9.807384704067667e-4 -2.132462972884878e-4
      1.374598300015347e-3 3.614306344974363e-3 -4.311626937634847e-3
      -1.361480077218489e-2 -1.863195957962409e-2 -5.732011516862200e-3
      -4.565025418422347e-3 -1.014641336426082e-2 2.346511528472817e-3
      1.984290810417874e-3 1.535414512147598e-2 -1.197624869410721e-2
      -2.379791036758995e-3 7.781774467330380e-3 4.589966938157353e-3
      1.418073773022240e-2 9.436894424244826e-3 2.814024499810398e-4
      3.484098005472213e-3 -6.419837515349230e-3 1.120322866309813e-2
      </forces>
    <stress rank="2" dims="3 3">
      -5.289331644479277e-7 2.340135504572502e-6 -2.476832444109098e-7
      2.340135504572502e-6 5.227090310271885e-7 -2.524032682326867e-7
      -2.476832444109098e-7 -2.524032682326867e-7 -1.615957126052802e-6
      </stress>
  </output>
  <exit_status>0</exit_status>
  <timing_info>
    <total label="PWSCF">
      <cpu>2.320830330000000e2</cpu>
      <wall>2.408308210372925e2</wall>
    </total>
    <partial label="init_run" calls="1">
      <cpu>1.429598300000000e1</cpu>
      <wall>1.476607608795166e1</wall>
    </partial>
    <partial label="hinit0" calls="1">
      <cpu>7.065380000000001e-1</cpu>
      <wall>7.265880107879639e-1</wall>
    </partial>
    <partial label="init_vloc" calls="1">
      <cpu>9.488999999999992e-2</cpu>
      <wall>9.489202499389648e-2</wall>
    </partial>
    <partial label="init_us_1" calls="1">
      <cpu>2.691700000000008e-2</cpu>
      <wall>2.691888809204102e-2</wall>
    </partial>
    <partial label="fft" calls="140">
      <cpu>9.406487999999968e0</cpu>
      <wall>1.014746022224426e1</wall>
    </partial>
    <partial label="fft_scatter" calls="8763">
      <cpu>4.693240800000138e1</cpu>
      <wall>4.975983023643494e1</wall>
    </partial>
    <partial label="potinit" calls="1">
      <cpu>2.203607000000000e0</cpu>
      <wall>2.255525112152100e0</wall>
    </partial>
    <partial label="v_of_rho" calls="9">
      <cpu>8.019471000000038e0</cpu>
      <wall>8.529693841934204e0</wall>
    </partial>
    <partial label="v_xc" calls="11">
      <cpu>8.935608000000030e0</cpu>
      <wall>9.496162891387939e0</wall>
    </partial>
    <partial label="v_h" calls="9">
      <cpu>7.696760000000040e-1</cpu>
      <wall>8.196361064910889e-1</wall>
    </partial>
    <partial label="PAW_pot" calls="9">
      <cpu>5.339869999999678e-1</cpu>
      <wall>5.340626239776611e-1</wall>
    </partial>
    <partial label="interpolate" calls="9">
      <cpu>1.630848999999984e0</cpu>
      <wall>1.660966634750366e0</wall>
    </partial>
    <partial label="ffts" calls="17">
      <cpu>1.174814999999967e0</cpu>
      <wall>1.184849977493286e0</wall>
    </partial>
    <partial label="newd" calls="9">
      <cpu>9.069940000000003e0</cpu>
      <wall>1.003046107292175e1</wall>
    </partial>
    <partial label="wfcinit" calls="1">
      <cpu>8.036925000000000e0</cpu>
      <wall>8.277872085571289e0</wall>
    </partial>
    <partial label="init_us_2" calls="76">
      <cpu>1.187201999999928e0</cpu>
      <wall>1.197515010833740e0</wall>
    </partial>
    <partial label="init_us_2:cp" calls="76">
      <cpu>1.186782999999991e0</cpu>
      <wall>1.197323799133301e0</wall>
    </partial>
    <partial label="wfcinit:atom" calls="4">
      <cpu>8.386200000000166e-2</cpu>
      <wall>9.386920928955078e-2</wall>
    </partial>
    <partial label="atomic_wfc" calls="4">
      <cpu>8.384900000000073e-2</cpu>
      <wall>9.386086463928223e-2</wall>
    </partial>
    <partial label="wfcinit:wfcr" calls="4">
      <cpu>7.529917999999997e0</cpu>
      <wall>7.740195035934448e0</wall>
    </partial>
    <partial label="wfcrot" calls="4">
      <cpu>7.529905000000003e0</cpu>
      <wall>7.740185976028442e0</wall>
    </partial>
    <partial label="rotwfck" calls="4">
      <cpu>7.529839000000003e0</cpu>
      <wall>7.740124225616455e0</wall>
    </partial>
    <partial label="rotwfck:hpsi" calls="4">
      <cpu>6.830710000000000e0</cpu>
      <wall>7.031033039093018e0</wall>
    </partial>
    <partial label="h_psi_bgrp" calls="273">
      <cpu>1.226613399999998e2</cpu>
      <wall>1.259133405685425e2</wall>
    </partial>
    <partial label="h_psi" calls="273">
      <cpu>1.226607740000000e2</cpu>
      <wall>1.259130632877350e2</wall>
    </partial>
    <partial label="h_psi:pot" calls="273">
      <cpu>1.220406349999997e2</cpu>
      <wall>1.252683057785034e2</wall>
    </partial>
    <partial label="vloc_psi" calls="273">
      <cpu>1.106191360000002e2</cpu>
      <wall>1.137430393695831e2</wall>
    </partial>
    <partial label="fftw" calls="8606">
      <cpu>1.064988419999986e2</cpu>
      <wall>1.097197949886322e2</wall>
    </partial>
    <partial label="h_psi:calbec" calls="273">
      <cpu>6.080140000000085e0</cpu>
      <wall>6.172718524932861e0</wall>
    </partial>
    <partial label="calbec" calls="325">
      <cpu>8.430385999999970e0</cpu>
      <wall>8.523407459259033e0</wall>
    </partial>
    <partial label="add_vuspsi" calls="273">
      <cpu>5.338565000000330e0</cpu>
      <wall>5.350732564926147e0</wall>
    </partial>
    <partial label="rotwfck:hc" calls="4">
      <cpu>5.490450000000013e-1</cpu>
      <wall>5.589909553527832e-1</wall>
    </partial>
    <partial label="s_psi_bgrp" calls="273">
      <cpu>5.225904000000156e0</cpu>
      <wall>5.305887460708618e0</wall>
    </partial>
    <partial label="s_psi" calls="273">
      <cpu>4.782393000000127e0</cpu>
      <wall>4.800060749053955e0</wall>
    </partial>
    <partial label="rotwfck:diag" calls="4">
      <cpu>5.226000000000397e-3</cpu>
      <wall>5.224943161010742e-3</wall>
    </partial>
    <partial label="cdiaghg" calls="269">
      <cpu>2.823580000002153e-1</cpu>
      <wall>2.827301025390625e-1</wall>
    </partial>
    <partial label="rotwfck:evc" calls="4">
      <cpu>1.444619999999972e-1</cpu>
      <wall>1.444852352142334e-1</wall>
    </partial>
    <partial label="electrons" calls="1">
      <cpu>1.948263520000000e2</cpu>
      <wall>2.022847959995270e2</wall>
    </partial>
    <partial label="c_bands" calls="8">
      <cpu>1.429785529999999e2</cpu>
      <wall>1.461740720272064e2</wall>
    </partial>
    <partial label="cegterg" calls="32">
      <cpu>1.407856010000001e2</cpu>
      <wall>1.439494967460632e2</wall>
    </partial>
    <partial label="cegterg:init" calls="32">
      <cpu>1.345271000000025e0</cpu>
      <wall>1.345390796661377e0</wall>
    </partial>
    <partial label="cegterg:upda" calls="237">
      <cpu>3.606319999999954e0</cpu>
      <wall>3.626663923263550e0</wall>
    </partial>
    <partial label="g_psi" calls="237">
      <cpu>3.964269999995906e-1</cpu>
      <wall>3.971333503723145e-1</wall>
    </partial>
    <partial label="cegterg:over" calls="237">
      <cpu>5.994334000000009e0</cpu>
      <wall>6.005141496658325e0</wall>
    </partial>
    <partial label="cegterg:diag" calls="265">
      <cpu>2.776780000000940e-1</cpu>
      <wall>2.779757976531982e-1</wall>
    </partial>
    <partial label="cegterg:last" calls="96">
      <cpu>6.177239000000100e0</cpu>
      <wall>6.177538156509399e0</wall>
    </partial>
    <partial label="sum_band" calls="8">
      <cpu>3.335450799999998e1</cpu>
      <wall>3.537552309036255e1</wall>
    </partial>
    <partial label="sum_band:wei" calls="8">
      <cpu>3.010000000074342e-4</cpu>
      <wall>2.858638763427734e-4</wall>
    </partial>
    <partial label="sum_band:loo" calls="8">
      <cpu>2.048978700000004e1</cpu>
      <wall>2.092968773841858e1</wall>
    </partial>
    <partial label="sum_band:buf" calls="32">
      <cpu>2.126950000000818e-1</cpu>
      <wall>2.129142284393311e-1</wall>
    </partial>
    <partial label="sum_band:ini" calls="32">
      <cpu>5.106229999999812e-1</cpu>
      <wall>5.107061862945557e-1</wall>
    </partial>
    <partial label="sum_band:cal" calls="32">
      <cpu>1.370442000000082e0</cpu>
      <wall>1.370484590530396e0</wall>
    </partial>
    <partial label="sum_band:bec" calls="32">
      <cpu>1.278000000041857e-3</cpu>
      <wall>1.288652420043945e-3</wall>
    </partial>
    <partial label="addusdens" calls="8">
      <cpu>1.147519399999999e1</cpu>
      <wall>1.300608682632446e1</wall>
    </partial>
    <partial label="addusd:skk" calls="24">
      <cpu>4.715730000000065e-1</cpu>
      <wall>7.718551158905029e-1</wall>
    </partial>
    <partial label="addusd:dgemm" calls="24">
      <cpu>2.511784999999975e0</cpu>
      <wall>3.725284814834595e0</wall>
    </partial>
    <partial label="addusd:qvan2" calls="24">
      <cpu>7.976711000000023e0</cpu>
      <wall>7.978782653808594e0</wall>
    </partial>
    <partial label="sum_band:sym" calls="8">
      <cpu>1.065446000000009e0</cpu>
      <wall>1.115611791610718e0</wall>
    </partial>
    <partial label="mix_rho" calls="8">
      <cpu>1.693207000000001e0</cpu>
      <wall>1.762942075729370e0</wall>
    </partial>
    <partial label="ions" calls="1">
      <cpu>2.286795200000000e1</cpu>
      <wall>2.350886487960815e1</wall>
    </partial>
    <partial label="forces" calls="1">
      <cpu>6.332576999999986e0</cpu>
      <wall>6.603541135787964e0</wall>
    </partial>
    <partial label="frc_us" calls="1">
      <cpu>2.662768999999997e0</cpu>
      <wall>2.873620986938477e0</wall>
    </partial>
    <partial label="frc_lc" calls="1">
      <cpu>7.371119999999962e-1</cpu>
      <wall>7.470979690551758e-1</wall>
    </partial>
    <partial label="frc_cc" calls="1">
      <cpu>1.398657999999983e0</cpu>
      <wall>1.448689937591553e0</wall>
    </partial>
    <partial label="frc_scc" calls="1">
      <cpu>1.044323999999989e0</cpu>
      <wall>1.044417858123779e0</wall>
    </partial>
    <partial label="stress" calls="1">
      <cpu>1.653536000000003e1</cpu>
      <wall>1.690530896186829e1</wall>
    </partial>
    <partial label="stres_us31" calls="4">
      <cpu>1.287999999988187e-3</cpu>
      <wall>1.299142837524414e-3</wall>
    </partial>
    <partial label="stres_us32" calls="4">
      <cpu>9.098000000022921e-3</cpu>
      <wall>9.151697158813477e-3</wall>
    </partial>
    <partial label="stres_us33" calls="4">
      <cpu>2.117099999998118e-2</cpu>
      <wall>2.118062973022461e-2</wall>
    </partial>
    <partial label="stres_us34" calls="4">
      <cpu>9.631000000001677e-2</cpu>
      <wall>1.062006950378418e-1</wall>
    </partial>
  </timing_info>
  <closed DATE="26 Jul 2024" TIME="21: 5: 4"></closed>
</qes:espresso>
